SpringDataRedis215ReleaseZhongwenWendang/README.md
SpringDataRedis215ReleaseZhongwenWendang/__init__.py
SpringDataRedis215ReleaseZhongwenWendang/__main__.py
SpringDataRedis215ReleaseZhongwenWendang/file.epub
SpringDataRedis215ReleaseZhongwenWendang/index.html
SpringDataRedis215ReleaseZhongwenWendang/css/__init__.py
SpringDataRedis215ReleaseZhongwenWendang/css/annotations.css
SpringDataRedis215ReleaseZhongwenWendang/css/main.css
SpringDataRedis215ReleaseZhongwenWendang/css/normalize.css
SpringDataRedis215ReleaseZhongwenWendang/css/popup.css
SpringDataRedis215ReleaseZhongwenWendang/font/__init__.py
SpringDataRedis215ReleaseZhongwenWendang/font/fontello.eot
SpringDataRedis215ReleaseZhongwenWendang/font/fontello.svg
SpringDataRedis215ReleaseZhongwenWendang/font/fontello.ttf
SpringDataRedis215ReleaseZhongwenWendang/font/fontello.woff
SpringDataRedis215ReleaseZhongwenWendang/img/__init__.py
SpringDataRedis215ReleaseZhongwenWendang/img/annotator-glyph-sprite.png
SpringDataRedis215ReleaseZhongwenWendang/img/annotator-icon-sprite.png
SpringDataRedis215ReleaseZhongwenWendang/img/apple-touch-icon.png
SpringDataRedis215ReleaseZhongwenWendang/img/cancelfullscreen.png
SpringDataRedis215ReleaseZhongwenWendang/img/close.png
SpringDataRedis215ReleaseZhongwenWendang/img/fullscreen.png
SpringDataRedis215ReleaseZhongwenWendang/img/loader.gif
SpringDataRedis215ReleaseZhongwenWendang/img/menu-icon.png
SpringDataRedis215ReleaseZhongwenWendang/img/save.png
SpringDataRedis215ReleaseZhongwenWendang/img/saved.png
SpringDataRedis215ReleaseZhongwenWendang/img/settings-s.png
SpringDataRedis215ReleaseZhongwenWendang/img/settings.png
SpringDataRedis215ReleaseZhongwenWendang/img/star.png
SpringDataRedis215ReleaseZhongwenWendang/js/__init__.py
SpringDataRedis215ReleaseZhongwenWendang/js/epub.js
SpringDataRedis215ReleaseZhongwenWendang/js/epub.min.js
SpringDataRedis215ReleaseZhongwenWendang/js/epub.min.map
SpringDataRedis215ReleaseZhongwenWendang/js/hooks.min.js
spring_data_redis_2_1_5_release_zhongwen_wendang-2024.3.5.0.dist-info/METADATA
spring_data_redis_2_1_5_release_zhongwen_wendang-2024.3.5.0.dist-info/WHEEL
spring_data_redis_2_1_5_release_zhongwen_wendang-2024.3.5.0.dist-info/entry_points.txt
spring_data_redis_2_1_5_release_zhongwen_wendang-2024.3.5.0.dist-info/top_level.txt
spring_data_redis_2_1_5_release_zhongwen_wendang-2024.3.5.0.dist-info/RECORD
